nokdoc/__init__.py
nokdoc/nokdoc.py
nokdoc/template/favicon.png
nokdoc/template/index.html
nokdoc/template/nokdoc_docset.html
nokdoc-0.3.0.dist-info/DESCRIPTION.rst
nokdoc-0.3.0.dist-info/METADATA
nokdoc-0.3.0.dist-info/RECORD
nokdoc-0.3.0.dist-info/WHEEL
nokdoc-0.3.0.dist-info/entry_points.txt
nokdoc-0.3.0.dist-info/metadata.json
nokdoc-0.3.0.dist-info/top_level.txt
