Metadata-Version: 2.0
Name: nokdoc
Version: 0.3.0
Summary: CLI Tool for interaction with Nokia doc portal
Home-page: UNKNOWN
Author: Roman Dodin
Author-email: dodin.roman@gmail.com
License: UNKNOWN
Platform: UNKNOWN
Requires-Dist: Click
Requires-Dist: certifi
Requires-Dist: jinja2
Requires-Dist: natsort
Requires-Dist: pyyaml
Requires-Dist: requests
Requires-Dist: tqdm
